{
  "title": "Understanding India’s Low-Carbon Energy Technology Startup Landscape",
  "canonical_url": "https://www.belfercenter.org/publication/understanding-indias-low-carbon-energy-technology-startup-landscape",
  "summary": "Low-carbon energy technology (LCET) startups could play a key role in accelerating India’s decarbonization. Yet, understanding of the LCET startup landscape and what shapes it remains low. This paper provides an analysis of the Indian LCET startup landscape to fill this gap.",
  "published": "2022-12-15T12:00:00Z",
  "authors": [
    "Robert Stowe"
  ],
  "author_profile_urls": [],
  "keywords": [
    "Energy",
    "Environment & Climate Change",
    "Environment and Natural Resources",
    "India's Energy Policy",
    "Renewable Energy",
    "Science, Technology, and Public Policy",
    "South Asia"
  ],
  "topics": [
    "Energy",
    "Environment & Climate Change",
    "India's Energy Policy",
    "Renewable Energy"
  ],
  "tags": [
    "Energy",
    "Environment & Climate Change",
    "Environment and Natural Resources",
    "India's Energy Policy",
    "Renewable Energy",
    "Science, Technology, and Public Policy",
    "South Asia"
  ],
  "body": "Abstract Low-carbon energy technology (LCET) startups could play a key role in accelerating India’s decarbonization. Yet, our understanding of the LCET startup landscape and what shapes it remains low. Herein, we provide an analysis of the Indian LCET startup landscape to fill this gap. Our descriptive analysis of quantitative data on investment and patenting activities of LCET startups from 2010 to 2020 and qualitative data from 25 semi-structured interviews shows a significant increase in investment and patenting activity, particularly after 2017, driven in large part by market-creation measures undertaken by the Indian government. However, there are large differences between LCET startups in different sub-sectors and core value-creating activities. Our findings suggest that the level of technological capabilities moderates the relationship between market creation measures and innovation outcomes—thus highlighting the need to complement market creation policies with long-term measures to strengthen technological capabilities. Furthermore, we propose a research agenda to improve our understanding of LCET entrepreneurship in developing economies. The latest from Belfer See more Recommended citation Krishna, Harilal, Yash Kashyap, Dwarkeshwar Dutt, Ambuj D. Sagar and Abhishek Malhotra. “Understanding India’s Low-Carbon Energy Technology Startup Landscape.” Nature Energy , December 15, 2022 Copy to Clipboard Understanding India’s Low-Carbon Energy Technology Startup Landscape View Citation Print Want to read more? The full text of this publication is available via Nature Energy. Read full article Energy Environment & Climate Change Environment and Natural Resources India's Energy Policy Renewable Energy Science, Technology, and Public Policy South Asia Recommended citation Krishna, Harilal, Yash Kashyap, Dwarkeshwar Dutt, Ambuj D. Sagar and Abhishek Malhotra. “Understanding India’s Low-Carbon Energy Technology Startup Landscape.” Nature Energy , December 15, 2022 Copy to Clipboard Author Harilal Krishna Author Yash Kashyap Author Dwarkeshwar Dutt Author Ambuj D. Sagar More From This Expert Building Institutional Capacity for Addressing Climate and Sustainable Development Goals: Achieving Energy Efficiency in India Linkages between the Indian Innovation System and MNE R&D Centers in India Author Abhishek Malhotra More From This Expert Catching-Up in Green Industries: The Role of Product Architecture Trade-Offs and Synergies in Power Sector Policy Mixes: The Case of Uttar Pradesh, India Up Next Photo Credit Toggle AP/Hau Dinh Article Navigating the Grid’s Perfect Storm: A Webinar with Andy Sun Dec. 11, 2025 by Robert Stowe From Harvard Project on Climate Agreements Photo Credit Toggle AP/Hau Dinh Reports & Papers Navigating the Grid’s Perfect Storm: Building a Resilient and Reliable Power System November 2025 by Sun, Andy Photo Credit Toggle Doug Gavel Q&A Climate Policy Progress and Challenges: A Conversation with John Podesta Sep. 18, 2025 by Robert N Stavins and John D. Podesta",
  "node_id": ""
}