{
  "title": "Helping States Tackle Technical Issues",
  "canonical_url": "https://www.belfercenter.org/publication/helping-states-tackle-technical-issues",
  "summary": "State legislatures need better access to scientific and technological expertise to make more informed decisions in the face of rapid and dramatic technological change. Ways to give state legislatures access to better information, including state universities, are discussed.",
  "published": "2025-12-23T12:00:00Z",
  "authors": [
    "Robert Stowe"
  ],
  "author_profile_urls": [],
  "keywords": [
    "Chemical & biological weapons",
    "Climate Change Policy",
    "Energy",
    "Energy Innovation Policy",
    "Environment & Climate Change",
    "Globalization",
    "International Security & Defense",
    "Science & Technology",
    "Science & Technology Policy",
    "Science, Technology, and Public Policy",
    "U.S. Energy Policy"
  ],
  "topics": [
    "Chemical & biological weapons",
    "Climate Change Policy",
    "Energy",
    "Energy Innovation Policy",
    "Environment & Climate Change",
    "Globalization",
    "International Security & Defense",
    "Science & Technology",
    "Science & Technology Policy",
    "U.S. Energy Policy"
  ],
  "tags": [
    "Chemical & biological weapons",
    "Climate Change Policy",
    "Energy",
    "Energy Innovation Policy",
    "Environment & Climate Change",
    "Globalization",
    "International Security & Defense",
    "Science & Technology",
    "Science & Technology Policy",
    "Science, Technology, and Public Policy",
    "U.S. Energy Policy"
  ],
  "body": "State legislatures need better access to scientific and technological expertise to make more informed decisions in the face of rapid and dramatic technological change. Ways to give state legislatures access to better information, including state universities, are discussed. To view full text please see PDF below (login may be required). The latest from Belfer See more Recommended citation Branscomb, Lewis and David Guston. “Helping States Tackle Technical Issues.” Issues in Science and Technology , Summer 1996 Copy to Clipboard Helping States Tackle Technical Issues View Citation Print Chemical & biological weapons Climate Change Policy Energy Energy Innovation Policy Environment & Climate Change Globalization International Security & Defense Science & Technology Science & Technology Policy Science, Technology, and Public Policy U.S. Energy Policy Recommended citation Branscomb, Lewis and David Guston. “Helping States Tackle Technical Issues.” Issues in Science and Technology , Summer 1996 Copy to Clipboard Author Lewis M. Branscomb More From This Expert Dangerous Cargo: Action Needed on Hazardous Materials Rail Transportation of Toxic Inhalation Hazards: Policy Responses to the Safety and Security Externality Author David Guston More From This Expert The Demand for and Supply of Technical Information and Analysis in State Legislatures Informed Legislatures: Coping with Science in a Democracy Up Next Photo Credit Toggle Ariana Diaz Article Harvard Project Director to Lead Executive Education Program on Climate Policy Dec. 23, 2025 by Robert Stowe From Harvard Project on Climate Agreements Photo Credit Toggle Maria Lidiane Rodrigues Event Summary Harvard Methane Initiative Conducts Research Workshop in São Paulo, Brazil Dec. 23, 2025 by Robert Stowe Photo Credit Toggle AP/Hau Dinh Article Navigating the Grid’s Perfect Storm: A Webinar with Andy Sun Dec. 11, 2025 by Robert Stowe",
  "node_id": ""
}