{
  "title": "Uncertainty and the Size Distribution of Rewards from Technological Innovation",
  "canonical_url": "https://www.belfercenter.org/publication/uncertainty-and-size-distribution-rewards-technological-innovation",
  "summary": "This page is for archival purposes as its content is no longer available. Please contact us for more information or use the search box in case this isn't what you are looking for.",
  "published": "2016-11-30",
  "authors": [
    "Robert Stowe"
  ],
  "author_profile_urls": [],
  "keywords": [
    "Chemical & biological weapons",
    "Climate Change Policy",
    "Energy",
    "Energy Innovation Policy",
    "Environment & Climate Change",
    "Globalization",
    "International Security & Defense",
    "Natural resource management",
    "Science & Technology",
    "Science & Technology Policy",
    "Science, Technology, and Public Policy",
    "Sustainable Development",
    "U.S. Energy Policy"
  ],
  "topics": [
    "Chemical & biological weapons",
    "Climate Change Policy",
    "Energy",
    "Energy Innovation Policy",
    "Environment & Climate Change",
    "Globalization",
    "International Security & Defense",
    "Natural resource management",
    "Science & Technology",
    "Science & Technology Policy",
    "Sustainable Development",
    "U.S. Energy Policy"
  ],
  "tags": [
    "Chemical & biological weapons",
    "Climate Change Policy",
    "Energy",
    "Energy Innovation Policy",
    "Environment & Climate Change",
    "Globalization",
    "International Security & Defense",
    "Natural resource management",
    "Science & Technology",
    "Science & Technology Policy",
    "Science, Technology, and Public Policy",
    "Sustainable Development",
    "U.S. Energy Policy"
  ],
  "body": "This page is for archival purposes as its content is no longer available. Please contact us for more information or use the search box in case this isn't what you are looking for. The latest from Belfer See more Recommended citation Scherer, F.M.. “Uncertainty and the Size Distribution of Rewards from Technological Innovation.” Journal of Evolutionary Economics , Copy to Clipboard Uncertainty and the Size Distribution of Rewards from Technological Innovation View Citation Print Chemical & biological weapons Climate Change Policy Energy Energy Innovation Policy Environment & Climate Change Globalization International Security & Defense Natural resource management Science & Technology Science & Technology Policy Science, Technology, and Public Policy Sustainable Development U.S. Energy Policy Recommended citation Scherer, F.M.. “Uncertainty and the Size Distribution of Rewards from Technological Innovation.” Journal of Evolutionary Economics , Copy to Clipboard Author F.M. Scherer More From This Expert New Perspectives on Economic Growth and Technological Innovation Technology Policy for a World of Skew-Distributed Incomes Up Next Photo Credit Toggle Ariana Diaz Article Harvard Project Director to Lead Executive Education Program on Climate Policy Dec. 23, 2025 by Robert Stowe From Harvard Project on Climate Agreements Photo Credit Toggle Maria Lidiane Rodrigues Event Summary Harvard Methane Initiative Conducts Research Workshop in São Paulo, Brazil Dec. 23, 2025 by Robert Stowe Photo Credit Toggle AP/Hau Dinh Article Navigating the Grid’s Perfect Storm: A Webinar with Andy Sun Dec. 11, 2025 by Robert Stowe",
  "node_id": ""
}